micromcp/__init__.py
micromcp/server.py
micromcp-1.0.0.dist-info/licenses/LICENSE
micromcp-1.0.0.dist-info/METADATA
micromcp-1.0.0.dist-info/WHEEL
micromcp-1.0.0.dist-info/top_level.txt
micromcp-1.0.0.dist-info/RECORD
