Metadata-Version: 2.4
Name: micromcp
Version: 1.0.0
Summary: Eine leichtgewichtige, FastMCP-kompatible Model Context Protocol (MCP) Server-Bibliothek für MicroPython (ESP32, etc.).
Author: lavariall
License: MIT License
Keywords: micropython,esp32,mcp,fastmcp,llm,websocket
Classifier: Development Status :: 3 - Alpha
Classifier: Programming Language :: Python :: Implementation :: MicroPython
Classifier: License :: OSI Approved :: MIT License
Classifier: Operating System :: Other OS
Classifier: Topic :: System :: Networking
Classifier: Topic :: Scientific/Engineering :: Artificial Intelligence
Classifier: Intended Audience :: Developers
Requires-Python: >=3.5
License-File: LICENSE
Provides-Extra: build
Requires-Dist: build; extra == "build"
Requires-Dist: twine; extra == "build"
Dynamic: license-file
